README.rst
setup.cfg
setup.py
doceboSSO/__init__.py
doceboSSO/docebo_sso.py
doceboSSO/docebo_user.py
doceboSSO.egg-info/PKG-INFO
doceboSSO.egg-info/SOURCES.txt
doceboSSO.egg-info/dependency_links.txt
doceboSSO.egg-info/requires.txt
doceboSSO.egg-info/top_level.txt
sso_test/__init__.py
sso_test/sso_method_tests.py