Metadata-Version: 1.1
Name: doceboSSO
Version: 0.0.1
Summary: Single Sign On Implementation for the Docebo LMS
Home-page: http://github.com/optimizely/docebo-SSO
Author: Chris Dee
Author-email: chris.dee@optimizely.com
License: UNKNOWN
Platform: UNKNOWN
Classifier: Development Status :: 4 - Beta
Classifier: Environment :: Web Environment
Classifier: Intended Audience :: Developers
Classifier: Operating System :: OS Independent
Classifier: Programming Language :: Python
Classifier: Programming Language :: Python :: 2.7
